{"result_id": "MNTT004019", "URL": "https://globalfood.wsj.com/", "timestamp": "2024-03-06 15:10:05 CET+0100", "meta": {"description": "Join The Wall Street Journal for headline-making conversations with leaders redefining the food industry and global agricultural economy.", "lang": "en", "favicon": "https://images.dowjones.com/wp-content/uploads/sites/329/2024/01/31020026/wsj-favicon.png", "canonical": "https://globalfood.wsj.com", "encoding": "utf-8", "website_keywords": ""}, "image": null, "domain": "globalfood.wsj.com", "title": "June 25\u201326, 2024", "cleaned_text": "", "opengraph": {"locale": "en_US", "type": "website", "title": "WSJ Global Food Forum | June 25\u201326, 2024", "description": "Join The Wall Street Journal for headline-making conversations with leaders redefining the food industry and global agricultural economy.", "url": "https://globalfood.wsj.com", "site_name": "WSJ Global Food Forum", "image": "https://images.dowjones.com/wp-content/uploads/sites/329/2024/02/07092648/06202123_WSJ_GlobalFoodForum_108-scaled-1.png", "image:width": "2560", "image:height": "1707", "image:type": "image/png"}, "tags": [], "tweets": [], "movies": [], "links": [], "authors": [], "publish_date": null}